rubiks_cube/__init__.py
rubiks_cube/cubie_cube.py
rubiks_cube/face_cube.py
rubiks_cube/rubiks_cube.py
rubiks_cube-1.0.7.dist-info/LICENSE
rubiks_cube-1.0.7.dist-info/METADATA
rubiks_cube-1.0.7.dist-info/WHEEL
rubiks_cube-1.0.7.dist-info/top_level.txt
rubiks_cube-1.0.7.dist-info/RECORD
