Metadata-Version: 2.1
Name: rubiks-cube
Version: 1.0.7
Summary: A Rubiks Cube Package for Python
Home-page: https://github.com/IguanaAzul/RubiksCube.git
Author: Ramon Griffo
Author-email: ramon.griffo98@gmail.com
License: MIT License
Platform: UNKNOWN
Requires-Dist: numpy
